{"type": "FeatureCollection", "id": "https://raw.githubusercontent.com/poseidon-framework/community-archive/master/2010_RasmussenNature/2010_RasmussenNature.janno", "name": "2010_RasmussenNature.janno", "features": [{"type": "Feature", "id": "http://archaeonatural.cloud/poseidon/DiscoverySite_89419a2e-8a00-5472-843f-8c7bfac91516", "name": "", "dateprops": [], "properties": {"http://archaeonatural.cloud/ont/atSite": ["nf6a1ff6999004772badfb3f3b4ec01feb241"], "http://archaeonatural.cloud/ont/hasRepresentativePoint": ["http://archaeonatural.cloud/poseidon/Geom_9c3432b2-351e-57ec-9f8d-e60c7e7e6844"], "http://purl.org/dc/terms/creator": ["http://orcid.org/0000-0002-3246-3531", "http://orcid.org/0009-0005-1140-3352"], "http://purl.org/dc/terms/license": ["https://creativecommons.org/licenses/by/4.0/"], "http://purl.org/dc/terms/rightsHolder": ["https://github.com/poseidon-framework/community-archive"], "http://rdfs.org/ns/void#inDataset": ["http://archaeonatural.cloud/poseidon/Poseidon_Demo-Dataset"], "http://www.opengis.net/ont/geosparql#hasGeometry": ["http://archaeonatural.cloud/poseidon/Geom_9c3432b2-351e-57ec-9f8d-e60c7e7e6844"], "http://www.w3.org/1999/02/22-rdf-syntax-ns#type": ["http://archaeonatural.cloud/ont/DiscoverySite", "http://www.w3.org/ns/prov#Entity"], "http://www.w3.org/2000/01/rdf-schema#comment": ["Entry created from the textual information in dataset https://raw.githubusercontent.com/poseidon-framework/community-archive/master/2010_RasmussenNature/2010_RasmussenNature.janno version 2.1.1 within the Poseidon Community Archive"], "http://www.w3.org/2000/01/rdf-schema#label": ["Discovery Site at POINT (-53.5413 69.2438)"], "http://www.w3.org/2004/02/skos/core#prefLabel": ["Discovery Site at POINT (-53.5413 69.2438)"], "http://www.w3.org/ns/prov#wasAttributedTo": ["http://archaeonatural.cloud/ont/SoftwareSourceCode_Poseidon_LOD"], "http://www.w3.org/ns/prov#wasDerivedFrom": ["https://github.com/archaeonatural-cloud/poseidon-lod/blob/main/data/EnrichedPoseidonCommunityArchiveData.csv", "https://github.com/poseidon-framework/community-archive", "https://raw.githubusercontent.com/poseidon-framework/community-archive/master/2010_RasmussenNature/2010_RasmussenNature.janno"], "http://www.w3.org/ns/prov#wasGeneratedBy": ["http://archaeonatural.cloud/poseidon/Activity_699aae7d-ad80-5955-8322-0b2cd06b652d"]}, "geometry": {"type": "Point", "coordinates": [-53.5413, 69.2438], "crs": "4326"}, "crs": "EPSG:4326"}], "numberMatched": 1, "numberReturned": 1, "bbox": [-53.5413, 69.2438, -53.5413, 69.2438], "crs": "http://www.opengis.net/def/crs/EPSG/0/EPSG:4326"}